{
  "meta": {
    "data_version": "1.1.0",
    "created": "2022-07-16",
    "revision": 1
  },
  "info": {
    "balls_per_over": 6,
    "city": "Bready",
    "dates": [
      "2022-07-16"
    ],
    "event": {
      "name": "Ireland Tri-Nation Women's T20I Series",
      "match_number": 1
    },
    "gender": "female",
    "match_type": "T20",
    "match_type_number": 1164,
    "officials": {
      "match_referees": [
        "Philip Thompson"
      ],
      "reserve_umpires": [
        "Jonathan Kennedy"
      ],
      "umpires": [
        "Aidan Seaver",
        "M Hawthorne"
      ]
    },
    "outcome": {
      "result": "no result"
    },
    "overs": 20,
    "players": {
      "Pakistan": [
        "Iram Javed",
        "Muneeba Ali",
        "Bismah Maroof",
        "Nida Dar",
        "Kainat Imtiaz",
        "Ayesha Naseem",
        "Aliya Riaz",
        "Fatima Sana",
        "Diana Baig",
        "Anam Amin",
        "Tuba Hassan"
      ],
      "Australia": [
        "AJ Healy",
        "BL Mooney",
        "RL Haynes",
        "MM Lanning",
        "D Brown",
        "TM McGrath",
        "A Gardner",
        "A King",
        "NJ Carey",
        "ML Schutt",
        "GM Harris"
      ]
    },
    "registry": {
      "people": {
        "A Gardner": "bc969efb",
        "A King": "83558266",
        "AJ Healy": "321644de",
        "Aidan Seaver": "862c0b16",
        "Aliya Riaz": "2904b4b6",
        "Anam Amin": "06653fcc",
        "Ayesha Naseem": "8c2c0a03",
        "BL Mooney": "52d1dbc8",
        "Bismah Maroof": "3b770527",
        "D Brown": "2e81be88",
        "Diana Baig": "a51e6c6e",
        "Fatima Sana": "ea9c54de",
        "GM Harris": "72166006",
        "Iram Javed": "dc596fac",
        "Jonathan Kennedy": "f7ad4494",
        "Kainat Imtiaz": "9714e764",
        "M Hawthorne": "ea123ee4",
        "ML Schutt": "17608a6f",
        "MM Lanning": "27e003ce",
        "Muneeba Ali": "86fdf668",
        "NJ Carey": "dff806f4",
        "Nida Dar": "ed840f44",
        "Philip Thompson": "0c677650",
        "RL Haynes": "d7c6b0fb",
        "TM McGrath": "ca5acfa4",
        "Tuba Hassan": "0d56e9a5"
      }
    },
    "season": "2022",
    "team_type": "international",
    "teams": [
      "Pakistan",
      "Australia"
    ],
    "toss": {
      "decision": "bat",
      "winner": "Pakistan"
    },
    "venue": "Bready Cricket Club, Magheramason, Bready"
  },
  "innings": [
    {
      "team": "Pakistan",
      "overs": [
        {
          "over": 0,
          "deliveries": [
            {
              "batter": "Iram Javed",
              "bowler": "ML Schutt",
              "non_striker": "Muneeba Ali",
              "runs": {
                "batter": 0,
                "extras": 0,
                "total": 0
              }
            },
            {
              "batter": "Iram Javed",
              "bowler": "ML Schutt",
              "non_striker": "Muneeba Ali",
              "runs": {
                "batter": 0,
                "extras": 0,
                "total": 0
              }
            },
            {
              "batter": "Iram Javed",
              "bowler": "ML Schutt",
              "non_striker": "Muneeba Ali",
              "runs": {
                "batter": 1,
                "extras": 0,
                "total": 1
              }
            },
            {
              "batter": "Muneeba Ali",
              "bowler": "ML Schutt",
              "non_striker": "Iram Javed",
              "runs": {
                "batter": 0,
                "extras": 0,
                "total": 0
              }
            },
            {
              "batter": "Muneeba Ali",
              "bowler": "ML Schutt",
              "extras": {
                "legbyes": 1
              },
              "non_striker": "Iram Javed",
              "runs": {
                "batter": 0,
                "extras": 1,
                "total": 1
              }
            },
            {
              "batter": "Iram Javed",
              "bowler": "ML Schutt",
              "non_striker": "Muneeba Ali",
              "runs": {
                "batter": 1,
                "extras": 0,
                "total": 1
              }
            }
          ]
        },
        {
          "over": 1,
          "deliveries": [
            {
              "batter": "Iram Javed",
              "bowler": "D Brown",
              "extras": {
                "wides": 5
              },
              "non_striker": "Muneeba Ali",
              "runs": {
                "batter": 0,
                "extras": 5,
                "total": 5
              }
            },
            {
              "batter": "Iram Javed",
              "bowler": "D Brown",
              "non_striker": "Muneeba Ali",
              "runs": {
                "batter": 1,
                "extras": 0,
                "total": 1
              }
            },
            {
              "batter": "Muneeba Ali",
              "bowler": "D Brown",
              "extras": {
                "wides": 1
              },
              "non_striker": "Iram Javed",
              "runs": {
                "batter": 0,
                "extras": 1,
                "total": 1
              }
            },
            {
              "batter": "Muneeba Ali",
              "bowler": "D Brown",
              "extras": {
                "legbyes": 4
              },
              "non_striker": "Iram Javed",
              "runs": {
                "batter": 0,
                "extras": 4,
                "total": 4
              }
            },
            {
              "batter": "Muneeba Ali",
              "bowler": "D Brown",
              "extras": {
                "wides": 1
              },
              "non_striker": "Iram Javed",
              "runs": {
                "batter": 0,
                "extras": 1,
                "total": 1
              }
            },
            {
              "batter": "Muneeba Ali",
              "bowler": "D Brown",
              "non_striker": "Iram Javed",
              "runs": {
                "batter": 0,
                "extras": 0,
                "total": 0
              }
            },
            {
              "batter": "Muneeba Ali",
              "bowler": "D Brown",
              "non_striker": "Iram Javed",
              "runs": {
                "batter": 0,
                "extras": 0,
                "total": 0
              }
            },
            {
              "batter": "Muneeba Ali",
              "bowler": "D Brown",
              "extras": {
                "noballs": 1
              },
              "non_striker": "Iram Javed",
              "runs": {
                "batter": 4,
                "extras": 1,
                "total": 5
              }
            },
            {
              "batter": "Muneeba Ali",
              "bowler": "D Brown",
              "non_striker": "Iram Javed",
              "runs": {
                "batter": 0,
                "extras": 0,
                "total": 0
              }
            },
            {
              "batter": "Muneeba Ali",
              "bowler": "D Brown",
              "non_striker": "Iram Javed",
              "runs": {
                "batter": 0,
                "extras": 0,
                "total": 0
              }
            }
          ]
        },
        {
          "over": 2,
          "deliveries": [
            {
              "batter": "Iram Javed",
              "bowler": "A Gardner",
              "non_striker": "Muneeba Ali",
              "runs": {
                "batter": 4,
                "extras": 0,
                "total": 4
              }
            },
            {
              "batter": "Iram Javed",
              "bowler": "A Gardner",
              "non_striker": "Muneeba Ali",
              "runs": {
                "batter": 4,
                "extras": 0,
                "total": 4
              }
            },
            {
              "batter": "Iram Javed",
              "bowler": "A Gardner",
              "non_striker": "Muneeba Ali",
              "runs": {
                "batter": 0,
                "extras": 0,
                "total": 0
              }
            },
            {
              "batter": "Iram Javed",
              "bowler": "A Gardner",
              "non_striker": "Muneeba Ali",
              "runs": {
                "batter": 1,
                "extras": 0,
                "total": 1
              }
            },
            {
              "batter": "Muneeba Ali",
              "bowler": "A Gardner",
              "non_striker": "Iram Javed",
              "runs": {
                "batter": 0,
                "extras": 0,
                "total": 0
              }
            },
            {
              "batter": "Muneeba Ali",
              "bowler": "A Gardner",
              "non_striker": "Iram Javed",
              "runs": {
                "batter": 0,
                "extras": 0,
                "total": 0
              }
            }
          ]
        },
        {
          "over": 3,
          "deliveries": [
            {
              "batter": "Iram Javed",
              "bowler": "ML Schutt",
              "non_striker": "Muneeba Ali",
              "runs": {
                "batter": 0,
                "extras": 0,
                "total": 0
              },
              "wickets": [
                {
                  "player_out": "Iram Javed",
                  "kind": "bowled"
                }
              ]
            },
            {
              "batter": "Bismah Maroof",
              "bowler": "ML Schutt",
              "non_striker": "Muneeba Ali",
              "runs": {
                "batter": 0,
                "extras": 0,
                "total": 0
              }
            },
            {
              "batter": "Bismah Maroof",
              "bowler": "ML Schutt",
              "non_striker": "Muneeba Ali",
              "runs": {
                "batter": 0,
                "extras": 0,
                "total": 0
              }
            },
            {
              "batter": "Bismah Maroof",
              "bowler": "ML Schutt",
              "non_striker": "Muneeba Ali",
              "runs": {
                "batter": 0,
                "extras": 0,
                "total": 0
              }
            },
            {
              "batter": "Bismah Maroof",
              "bowler": "ML Schutt",
              "non_striker": "Muneeba Ali",
              "runs": {
                "batter": 1,
                "extras": 0,
                "total": 1
              }
            },
            {
              "batter": "Muneeba Ali",
              "bowler": "ML Schutt",
              "extras": {
                "wides": 3
              },
              "non_striker": "Bismah Maroof",
              "runs": {
                "batter": 0,
                "extras": 3,
                "total": 3
              }
            },
            {
              "batter": "Muneeba Ali",
              "bowler": "ML Schutt",
              "non_striker": "Bismah Maroof",
              "runs": {
                "batter": 0,
                "extras": 0,
                "total": 0
              }
            }
          ]
        },
        {
          "over": 4,
          "deliveries": [
            {
              "batter": "Bismah Maroof",
              "bowler": "A Gardner",
              "non_striker": "Muneeba Ali",
              "runs": {
                "batter": 0,
                "extras": 0,
                "total": 0
              },
              "wickets": [
                {
                  "player_out": "Bismah Maroof",
                  "kind": "bowled"
                }
              ]
            },
            {
              "batter": "Nida Dar",
              "bowler": "A Gardner",
              "non_striker": "Muneeba Ali",
              "runs": {
                "batter": 0,
                "extras": 0,
                "total": 0
              }
            },
            {
              "batter": "Nida Dar",
              "bowler": "A Gardner",
              "non_striker": "Muneeba Ali",
              "runs": {
                "batter": 1,
                "extras": 0,
                "total": 1
              }
            },
            {
              "batter": "Muneeba Ali",
              "bowler": "A Gardner",
              "extras": {
                "wides": 1
              },
              "non_striker": "Nida Dar",
              "runs": {
                "batter": 0,
                "extras": 1,
                "total": 1
              }
            },
            {
              "batter": "Muneeba Ali",
              "bowler": "A Gardner",
              "non_striker": "Nida Dar",
              "runs": {
                "batter": 0,
                "extras": 0,
                "total": 0
              }
            },
            {
              "batter": "Muneeba Ali",
              "bowler": "A Gardner",
              "non_striker": "Nida Dar",
              "runs": {
                "batter": 0,
                "extras": 0,
                "total": 0
              }
            },
            {
              "batter": "Muneeba Ali",
              "bowler": "A Gardner",
              "non_striker": "Nida Dar",
              "runs": {
                "batter": 0,
                "extras": 0,
                "total": 0
              },
              "wickets": [
                {
                  "player_out": "Muneeba Ali",
                  "kind": "bowled"
                }
              ]
            }
          ]
        },
        {
          "over": 5,
          "deliveries": [
            {
              "batter": "Nida Dar",
              "bowler": "TM McGrath",
              "non_striker": "Kainat Imtiaz",
              "runs": {
                "batter": 0,
                "extras": 0,
                "total": 0
              }
            },
            {
              "batter": "Nida Dar",
              "bowler": "TM McGrath",
              "non_striker": "Kainat Imtiaz",
              "runs": {
                "batter": 0,
                "extras": 0,
                "total": 0
              }
            },
            {
              "batter": "Nida Dar",
              "bowler": "TM McGrath",
              "non_striker": "Kainat Imtiaz",
              "runs": {
                "batter": 0,
                "extras": 0,
                "total": 0
              }
            },
            {
              "batter": "Nida Dar",
              "bowler": "TM McGrath",
              "non_striker": "Kainat Imtiaz",
              "runs": {
                "batter": 0,
                "extras": 0,
                "total": 0
              }
            },
            {
              "batter": "Nida Dar",
              "bowler": "TM McGrath",
              "non_striker": "Kainat Imtiaz",
              "runs": {
                "batter": 0,
                "extras": 0,
                "total": 0
              }
            },
            {
              "batter": "Nida Dar",
              "bowler": "TM McGrath",
              "non_striker": "Kainat Imtiaz",
              "runs": {
                "batter": 4,
                "extras": 0,
                "total": 4
              }
            }
          ]
        },
        {
          "over": 6,
          "deliveries": [
            {
              "batter": "Kainat Imtiaz",
              "bowler": "A King",
              "extras": {
                "wides": 5
              },
              "non_striker": "Nida Dar",
              "runs": {
                "batter": 0,
                "extras": 5,
                "total": 5
              }
            },
            {
              "batter": "Kainat Imtiaz",
              "bowler": "A King",
              "non_striker": "Nida Dar",
              "runs": {
                "batter": 0,
                "extras": 0,
                "total": 0
              },
              "wickets": [
                {
                  "player_out": "Kainat Imtiaz",
                  "kind": "lbw"
                }
              ]
            },
            {
              "batter": "Ayesha Naseem",
              "bowler": "A King",
              "extras": {
                "wides": 3
              },
              "non_striker": "Nida Dar",
              "runs": {
                "batter": 0,
                "extras": 3,
                "total": 3
              }
            },
            {
              "batter": "Ayesha Naseem",
              "bowler": "A King",
              "non_striker": "Nida Dar",
              "runs": {
                "batter": 0,
                "extras": 0,
                "total": 0
              },
              "wickets": [
                {
                  "player_out": "Ayesha Naseem",
                  "kind": "lbw"
                }
              ]
            },
            {
              "batter": "Aliya Riaz",
              "bowler": "A King",
              "non_striker": "Nida Dar",
              "runs": {
                "batter": 0,
                "extras": 0,
                "total": 0
              },
              "wickets": [
                {
                  "player_out": "Aliya Riaz",
                  "kind": "lbw"
                }
              ]
            },
            {
              "batter": "Fatima Sana",
              "bowler": "A King",
              "non_striker": "Nida Dar",
              "runs": {
                "batter": 0,
                "extras": 0,
                "total": 0
              }
            },
            {
              "batter": "Fatima Sana",
              "bowler": "A King",
              "non_striker": "Nida Dar",
              "runs": {
                "batter": 0,
                "extras": 0,
                "total": 0
              }
            },
            {
              "batter": "Fatima Sana",
              "bowler": "A King",
              "non_striker": "Nida Dar",
              "runs": {
                "batter": 0,
                "extras": 0,
                "total": 0
              }
            }
          ]
        },
        {
          "over": 7,
          "deliveries": [
            {
              "batter": "Nida Dar",
              "bowler": "D Brown",
              "non_striker": "Fatima Sana",
              "runs": {
                "batter": 0,
                "extras": 0,
                "total": 0
              }
            },
            {
              "batter": "Nida Dar",
              "bowler": "D Brown",
              "extras": {
                "wides": 1
              },
              "non_striker": "Fatima Sana",
              "runs": {
                "batter": 0,
                "extras": 1,
                "total": 1
              }
            },
            {
              "batter": "Nida Dar",
              "bowler": "D Brown",
              "extras": {
                "wides": 1
              },
              "non_striker": "Fatima Sana",
              "runs": {
                "batter": 0,
                "extras": 1,
                "total": 1
              }
            },
            {
              "batter": "Nida Dar",
              "bowler": "D Brown",
              "non_striker": "Fatima Sana",
              "runs": {
                "batter": 0,
                "extras": 0,
                "total": 0
              }
            },
            {
              "batter": "Nida Dar",
              "bowler": "D Brown",
              "extras": {
                "noballs": 1
              },
              "non_striker": "Fatima Sana",
              "runs": {
                "batter": 0,
                "extras": 1,
                "total": 1
              }
            },
            {
              "batter": "Nida Dar",
              "bowler": "D Brown",
              "non_striker": "Fatima Sana",
              "runs": {
                "batter": 2,
                "extras": 0,
                "total": 2
              }
            },
            {
              "batter": "Nida Dar",
              "bowler": "D Brown",
              "non_striker": "Fatima Sana",
              "runs": {
                "batter": 1,
                "extras": 0,
                "total": 1
              }
            },
            {
              "batter": "Fatima Sana",
              "bowler": "D Brown",
              "non_striker": "Nida Dar",
              "runs": {
                "batter": 1,
                "extras": 0,
                "total": 1
              }
            },
            {
              "batter": "Nida Dar",
              "bowler": "D Brown",
              "non_striker": "Fatima Sana",
              "runs": {
                "batter": 2,
                "extras": 0,
                "total": 2
              }
            }
          ]
        }
      ],
      "powerplays": [
        {
          "from": 0.1,
          "to": 5.6,
          "type": "mandatory"
        }
      ]
    }
  ]
}